{
  "id": "oauth-implementation-02",
  "url": "https://dev.clever.com/docs/oauth-implementation",
  "path": "/docs/oauth-implementation",
  "section": "OAuth and OIDC",
  "title": "OAuth Implementation",
  "heading": "OAuth Implementation",
  "headingLevel": 0,
  "parentHeadings": [
    "OAuth Implementation"
  ],
  "content": "> 🚧\n> \n> ### \n> \n> **Authorization codes expire quickly**\n> \n> [](#authorization-codes-expire-quickly)\n> \n> Authorization codes are valid for one minute and can only be exchanged once.\n\nExample response (`id_token` is only present when your app is configured for OIDC):\n\n```\n{\n  \"access_token\": \"access_token_here\",\n  \"id_token\": \"id_token_here\"\n}\n```\n\n> ❗️\n> \n> ### \n> \n> **Token expiration**\n> \n> [](#token-expiration)\n> \n> Tokens expire after 24 hours and cannot be refreshed. Do not use them for long-term user identification.\n> \n> Clever user sessions expire after 2 hours.\n\n## \n\nUse the returned tokens\n\n[](#use-the-returned-tokens)\n\n### \n\nAccess tokens\n\n[](#access-tokens-1)\n\nAfter you receive an access token, call `https://api.clever.com/v3.0/me` to retrieve the user’s Clever ID, district ID, and token type.\n\nIn most implementations, you should identify the token owner immediately after exchange.\n\n### \n\nIdentity tokens\n\n[](#identity-tokens-1)\n\nIf your app receives an identity token, decode and verify it using a JWT library rather than parsing it manually.\n\nA list of language-specific JWT libraries is available at [jwt.io/libraries](https://jwt.io/libraries).\n\n### \n\nBearer tokens\n\n[](#bearer-tokens)\n\nUse the access token as a bearer token in the `Authorization` header:\n\n```\nGET https://api.clever.com/some_clever_resource\nAuthorization: Bearer jsfUI2131da2f\n```\n\n## \n\nThe `authorized_by` field\n\n[](#the-authorized_by-field)\n\nDistricts must authorize Clever Single Sign-On connections before users can log in with them. Districts do this by connecting to your app at the district level and configuring sharing permissions.\n\nTo learn more:\n\n-   [Connecting with Districts](https://support.clever.com/hc/s/articles/215120718?language=en_US)\n-   [Sharing Permissions](https://support.clever.com/hc/s/articles/203115007?language=en_US)\n\nYou can identify a district-authorized SSO request by looking at the `/me` response. In a Clever Single Sign-On flow, `authorized_by` is set to `district`.\n\n```\n{\n  \"type\": \"user\",\n  \"data\": {\n    \"id\": \"5fc43758db087d0be186c29d\",\n    \"district\": \"5d0a9e5d0958b300014e49d2\",\n    \"type\": \"user\",\n    \"authorized_by\": \"district\"\n  },\n  \"links\": [\n    {\n      \"rel\": \"self\",\n      \"uri\": \"/me\"\n    },\n    {\n      \"rel\": \"canonical\",\n      \"uri\": \"/v3.0/users/5fc43758db087d0be186c29d\"\n    },\n    {\n      \"rel\": \"district\",\n      \"uri\": \"/v3.0/districts/5d0a9e5d0958b300014e49d2\"\n    }\n  ]\n}\n```",
  "tokenEstimate": 611,
  "crawledAt": "2026-04-20T06:43:26.709Z",
  "fetchMethod": "static",
  "chunkIndex": 2,
  "totalChunks": 3
}